{
  "gender": "female",
  "species": "rabbit",
  "birthday": "3-14",
  "home_request": "A two-tone room",
  "skill": "Home repair",
  "goal": "Tennis player",
  "coffee": {
    "beans": "Blue Mountain",
    "milk": "Lots of milk",
    "sugar": "Three spoonfuls of sugar"
  },
  "style": "Modern",
  "games": {
    "af": {
      "personality": "peppy",
      "clothes": "Blue-Check Tee",
      "song": "K.K. Technopop",
      "phrase": "wee one"
    },
    "af+": {
      "personality": "peppy",
      "clothes": "Blue-Check Tee",
      "song": "K.K. Technopop",
      "phrase": "wee one"
    },
    "ac": {
      "personality": "peppy",
      "clothes": "Blue-Check Tee",
      "song": "K.K. Technopop",
      "phrase": "wee one"
    },
    "afe+": {
      "personality": "peppy",
      "clothes": "Blue-Check Tee",
      "song": "K.K. Technopop",
      "phrase": "wee one"
    },
    "ww": {
      "personality": "peppy",
      "clothes": "Blue-Check Tee",
      "song": "K.K. Technopop",
      "phrase": "wee one"
    },
    "cf": {
      "personality": "peppy",
      "clothes": "Blue-Check Tee",
      "song": "K.K. Technopop",
      "phrase": "wee one"
    },
    "nl": {
      "personality": "peppy",
      "clothes": "Blue-Check Tee",
      "song": "K.K. Technopop",
      "phrase": "wee one"
    },
    "hhd": {
      "personality": "peppy",
      "clothes": "Blue-Check Tee",
      "song": "K.K. Technopop",
      "phrase": "wee one"
    },
    "pc": {
      "personality": "peppy",
      "clothes": "Blue-Check Tee",
      "song": "K.K. Technopop",
      "phrase": "wee one"
    }
  },
  "name": "Dotty",
  "id": "dotty"
}