{
  "gender": "male",
  "species": "rhino",
  "birthday": "3-20",
  "coffee": {
    "beans": "Blend",
    "milk": "A little bit of milk",
    "sugar": "1 spoonful of sugar"
  },
  "games": {
    "af": {
      "personality": "lazy",
      "clothes": "Chevron Shirt",
      "song": "Aloha K.K."
    },
    "af+": {
      "personality": "lazy",
      "clothes": "Chevron Shirt",
      "song": "Aloha K.K."
    },
    "ac": {
      "personality": "lazy",
      "clothes": "Chevron Shirt",
      "song": "Aloha K.K.",
      "phrase": "schnozzle"
    },
    "afe+": {
      "personality": "lazy",
      "clothes": "Chevron Shirt",
      "song": "Aloha K.K"
    },
    "nl": {
      "personality": "lazy",
      "clothes": "Chevron Shirt",
      "song": "K.K. Lament",
      "phrase": "schnozzle",
      "skill": "Bunting/Comedy",
      "goal": "Artist"
    }
  },
  "name": "Hornsby",
  "id": "hornsby"
}