{
  "gender": "male",
  "species": "penguin",
  "birthday": "2-21",
  "games": {
    "af": {
      "personality": "lazy",
      "clothes": "BB Tee",
      "song": "K.K. Casbah"
    },
    "af+": {
      "personality": "lazy",
      "clothes": "BB Tee",
      "song": "K.K. Casbah"
    },
    "ac": {
      "personality": "lazy",
      "clothes": "BB Tee",
      "song": "K.K. Casbah",
      "phrase": "brrrrrrrrr"
    },
    "afe+": {
      "personality": "lazy",
      "clothes": "BB Tee",
      "song": "K.K. Casbah"
    },
    "cf": {
      "personality": "lazy",
      "clothes": "BB Tee",
      "song": "K.K. Casbah",
      "phrase": "brrrrrrrrr"
    },
    "nl": {
      "personality": "lazy",
      "clothes": "BB Tee",
      "song": "K.K. Casbah",
      "phrase": "brrrrrrrrr",
      "skill": "Doing handstands",
      "goal": "Superhero",
      "fear": "Werewolf Hood",
      "quote": "A bad attitude will land you in the penalty box.",
      "siblings": "Middle kid",
      "favoriteStyle": "Sporty",
      "dislikedStyle": "Iconic",
      "favoriteColor": "blue",
      "coffee": {
        "beans": "Blend",
        "milk": "A little bit of milk",
        "sugar": "One sugar"
      }
    }
  },
  "name": "Puck",
  "id": "puck"
}